CONTRIBUTING.md
MANIFEST.in
README.rst
setup.py
docs/HISTORY.txt
docs/LICENSE.GPL
docs/LICENSE.txt
eea/__init__.py
eea.website.policy.egg-info/PKG-INFO
eea.website.policy.egg-info/SOURCES.txt
eea.website.policy.egg-info/dependency_links.txt
eea.website.policy.egg-info/entry_points.txt
eea.website.policy.egg-info/namespace_packages.txt
eea.website.policy.egg-info/not-zip-safe
eea.website.policy.egg-info/requires.txt
eea.website.policy.egg-info/top_level.txt
eea/website/__init__.py
eea/website/policy/README.txt
eea/website/policy/__init__.py
eea/website/policy/configure.zcml
eea/website/policy/interfaces.py
eea/website/policy/profiles.zcml
eea/website/policy/setuphandlers.py
eea/website/policy/version.txt
eea/website/policy/behaviors/__init__.py
eea/website/policy/behaviors/configure.zcml
eea/website/policy/browser/__init__.py
eea/website/policy/browser/configure.zcml
eea/website/policy/browser/view.pt
eea/website/policy/locales/__init__.py
eea/website/policy/locales/eea.pot
eea/website/policy/locales/plone-manual.pot
eea/website/policy/locales/update.sh
eea/website/policy/locales/bg/LC_MESSAGES/eea.mo
eea/website/policy/locales/bg/LC_MESSAGES/eea.po
eea/website/policy/locales/bg/LC_MESSAGES/plone.mo
eea/website/policy/locales/bg/LC_MESSAGES/plone.po
eea/website/policy/locales/cs/LC_MESSAGES/eea.mo
eea/website/policy/locales/cs/LC_MESSAGES/eea.po
eea/website/policy/locales/cs/LC_MESSAGES/plone.mo
eea/website/policy/locales/cs/LC_MESSAGES/plone.po
eea/website/policy/locales/da/LC_MESSAGES/eea.mo
eea/website/policy/locales/da/LC_MESSAGES/eea.po
eea/website/policy/locales/da/LC_MESSAGES/plone.mo
eea/website/policy/locales/da/LC_MESSAGES/plone.po
eea/website/policy/locales/de/LC_MESSAGES/eea.mo
eea/website/policy/locales/de/LC_MESSAGES/eea.po
eea/website/policy/locales/de/LC_MESSAGES/plone.mo
eea/website/policy/locales/de/LC_MESSAGES/plone.po
eea/website/policy/locales/el/LC_MESSAGES/eea.mo
eea/website/policy/locales/el/LC_MESSAGES/eea.po
eea/website/policy/locales/el/LC_MESSAGES/plone.mo
eea/website/policy/locales/el/LC_MESSAGES/plone.po
eea/website/policy/locales/en/LC_MESSAGES/eea.mo
eea/website/policy/locales/en/LC_MESSAGES/eea.po
eea/website/policy/locales/en/LC_MESSAGES/plone.mo
eea/website/policy/locales/en/LC_MESSAGES/plone.po
eea/website/policy/locales/es/LC_MESSAGES/eea.mo
