Metadata-Version: 2.4
Name: eea.website.policy
Version: 4.2
Summary: EEA Website Plone backend policy
Home-page: https://github.com/eea/eea.website.policy
Author: European Environment Agency: IDM2 A-Team
Author-email: eea-edw-a-team-alerts@googlegroups.com
License: GPL version 2
Keywords: EEA Add-ons Plone Zope
Classifier: Environment :: Web Environment
Classifier: Framework :: Plone
Classifier: Framework :: Plone :: Addon
Classifier: Framework :: Plone :: 5.2
Classifier: Framework :: Plone :: 6.0
Classifier: Programming Language :: Python
Classifier: Programming Language :: Python :: 3.7
Classifier: Programming Language :: Python :: 3.8
Classifier: Programming Language :: Python :: 3.9
Classifier: Operating System :: OS Independent
Classifier: License :: OSI Approved :: GNU General Public License v2 (GPLv2)
Requires-Dist: setuptools
Requires-Dist: eea.kitkat
Requires-Dist: eea.dexterity.indicators
Requires-Dist: eea.dexterity.themes
Requires-Dist: eea.progress.workflow
Requires-Dist: eea.progress.editing
Requires-Dist: eea.api.dataconnector
Requires-Dist: collective.volto.subsites
Provides-Extra: test
Requires-Dist: plone.app.contenttypes; extra == "test"
Requires-Dist: plone.app.testing; extra == "test"
Requires-Dist: plone.testing; extra == "test"
Requires-Dist: zope.testrunner; extra == "test"
Dynamic: author
Dynamic: author-email
Dynamic: classifier
Dynamic: description
Dynamic: description-content-type
Dynamic: home-page
Dynamic: keywords
Dynamic: license
Dynamic: provides-extra
Dynamic: requires-dist
Dynamic: summary
